MANIFEST.in
README.md
setup.py
CPU_INFO/__init__.py
CPU_INFO/manage.py
CPU_INFO/runserver.py
CPU_INFO/CPU/__init__.py
CPU_INFO/CPU/asgi.py
CPU_INFO/CPU/settings.py
CPU_INFO/CPU/urls.py
CPU_INFO/CPU/wsgi.py
CPU_INFO/api/__init__.py
CPU_INFO/api/apps.py
CPU_INFO/api/serializers.py
CPU_INFO/api/urls.py
CPU_INFO/api/views.py
CPU_INFO/api/migrations/__init__.py
CPU_INFO/cpu_utilization/__init__.py
CPU_INFO/cpu_utilization/admin.py
CPU_INFO/cpu_utilization/apps.py
CPU_INFO/cpu_utilization/models.py
CPU_INFO/cpu_utilization/urls.py
CPU_INFO/cpu_utilization/views.py
CPU_INFO/cpu_utilization/migrations/0001_initial.py
CPU_INFO/cpu_utilization/migrations/__init__.py
CPU_INFO/static/bootstrap-5.0.2-dist/css/bootstrap-grid.css
CPU_INFO/static/bootstrap-5.0.2-dist/css/bootstrap-grid.css.map
CPU_INFO/static/bootstrap-5.0.2-dist/css/bootstrap-grid.min.css
CPU_INFO/static/bootstrap-5.0.2-dist/css/bootstrap-grid.min.css.map
CPU_INFO/static/bootstrap-5.0.2-dist/css/bootstrap-grid.rtl.css
CPU_INFO/static/bootstrap-5.0.2-dist/css/bootstrap-grid.rtl.css.map
CPU_INFO/static/bootstrap-5.0.2-dist/css/bootstrap-grid.rtl.min.css
CPU_INFO/static/bootstrap-5.0.2-dist/css/bootstrap-grid.rtl.min.css.map
CPU_INFO/static/bootstrap-5.0.2-dist/css/bootstrap-reboot.css
CPU_INFO/static/bootstrap-5.0.2-dist/css/bootstrap-reboot.css.map
CPU_INFO/static/bootstrap-5.0.2-dist/css/bootstrap-reboot.min.css
CPU_INFO/static/bootstrap-5.0.2-dist/css/bootstrap-reboot.min.css.map
CPU_INFO/static/bootstrap-5.0.2-dist/css/bootstrap-reboot.rtl.css
CPU_INFO/static/bootstrap-5.0.2-dist/css/bootstrap-reboot.rtl.css.map
CPU_INFO/static/bootstrap-5.0.2-dist/css/bootstrap-reboot.rtl.min.css
CPU_INFO/static/bootstrap-5.0.2-dist/css/bootstrap-reboot.rtl.min.css.map
CPU_INFO/static/bootstrap-5.0.2-dist/css/bootstrap-utilities.css
CPU_INFO/static/bootstrap-5.0.2-dist/css/bootstrap-utilities.css.map
CPU_INFO/static/bootstrap-5.0.2-dist/css/bootstrap-utilities.min.css
cpu_info.egg-info/PKG-INFO
cpu_info.egg-info/SOURCES.txt
cpu_info.egg-info/dependency_links.txt
cpu_info.egg-info/requires.txt
cpu_info.egg-info/top_level.txt