Metadata-Version: 2.1
Name: cpu-info
Version: 0.1.1
Summary: Getting cpu information
Home-page: https://github.com/Maxon57/CPU
Author: Maxim Ignatov
Author-email: ignatov.mack@gmail.com
License: UNKNOWN
Platform: UNKNOWN
